swh/fuse/__init__.py
swh/fuse/cache.py
swh/fuse/cli.py
swh/fuse/fuse.py
swh/fuse/py.typed
swh/fuse/backends/__init__.py
swh/fuse/backends/compressed.py
swh/fuse/backends/objstorage.py
swh/fuse/backends/web_api.py
swh/fuse/fs/artifact.py
swh/fuse/fs/entry.py
swh/fuse/fs/mountpoint.py
swh/fuse/tests/graph/__init__.py
swh/fuse/tests/graph/conftest.py
swh/fuse/tests/graph/test_content.py
swh/fuse/tests/graph/test_directory.py
swh/fuse/tests/graph/test_origin.py
swh/fuse/tests/graph/test_release.py
swh/fuse/tests/graph/test_revision.py
swh/fuse/tests/graph/test_snapshot.py
swh/fuse/tests/tools/swh_fuse_context.py
swh/fuse/tests/web_api/__init__.py
swh/fuse/tests/web_api/api_url.py
swh/fuse/tests/web_api/common.py
swh/fuse/tests/web_api/conftest.py
swh/fuse/tests/web_api/test_cache.py
swh/fuse/tests/web_api/test_cli.py
swh/fuse/tests/web_api/test_content.py
swh/fuse/tests/web_api/test_directory.py
swh/fuse/tests/web_api/test_meta.py
swh/fuse/tests/web_api/test_mountpoint.py
swh/fuse/tests/web_api/test_origin.py
swh/fuse/tests/web_api/test_release.py
swh/fuse/tests/web_api/test_revision.py
swh/fuse/tests/web_api/test_snapshot.py
swh/fuse/tests/web_api/test_unusual.py
swh/fuse/tests/web_api/unusual_data.py
swh/fuse/tests/web_api/data/__init__.py
swh/fuse/tests/web_api/data/api_data.py
swh/fuse/tests/web_api/data/config.py
swh/fuse/tests/web_api/data/gen-api-data.py
swh_fuse-1.4.5.dist-info/licenses/AUTHORS
swh_fuse-1.4.5.dist-info/licenses/LICENSE
swh_fuse-1.4.5.dist-info/METADATA
swh_fuse-1.4.5.dist-info/WHEEL
swh_fuse-1.4.5.dist-info/entry_points.txt
swh_fuse-1.4.5.dist-info/top_level.txt
swh_fuse-1.4.5.dist-info/RECORD
